nebulous/__init__.py
nebulous/auth.py
nebulous/cache.py
nebulous/config.py
nebulous/data.py
nebulous/errors.py
nebulous/logging.py
nebulous/meta.py
nebulous/orign.py
nebulous/builders/builder.py
nebulous/builders/models.py
nebulous/containers/container.py
nebulous/containers/models.py
nebulous/namespaces/models.py
nebulous/namespaces/namespace.py
nebulous/processors/consumer.py
nebulous/processors/consumer_health_worker.py
nebulous/processors/consumer_process_worker.py
nebulous/processors/decorate.py
nebulous/processors/default.py
nebulous/processors/models.py
nebulous/processors/processor.py
nebulous/redis/models.py
nebulous/services/service.py
nebulous_sh-0.1.148.dist-info/licenses/LICENSE
nebulous_sh-0.1.148.dist-info/METADATA
nebulous_sh-0.1.148.dist-info/WHEEL
nebulous_sh-0.1.148.dist-info/top_level.txt
nebulous_sh-0.1.148.dist-info/RECORD
